alively/__init__.py
alively/__main__.py
alively/app.py
alively/events.py
alively/renderers.py
alively/runners.py
alively/state.py
alively/utils.py
alively-0.0.1.dist-info/METADATA
alively-0.0.1.dist-info/WHEEL
alively-0.0.1.dist-info/entry_points.txt
alively-0.0.1.dist-info/top_level.txt
alively-0.0.1.dist-info/RECORD
