Metadata-Version: 2.1
Name: alively
Version: 0.0.1
Summary: A dynamic, colorful cli for dbt
Author-email: Tom Waterman <tjwaterman99@gmail.com>
Requires-Python: >=3.7
Requires-Dist: pydantic ==2.9.2
Requires-Dist: rich ==13.8.1
